zulipchat_mcp/__init__.py
zulipchat_mcp/config.py
zulipchat_mcp/server.py
zulipchat_mcp/setup_wizard.py
zulipchat_mcp/core/__init__.py
zulipchat_mcp/core/agent_tracker.py
zulipchat_mcp/core/cache.py
zulipchat_mcp/core/client.py
zulipchat_mcp/core/emoji_registry.py
zulipchat_mcp/core/error_handling.py
zulipchat_mcp/core/exceptions.py
zulipchat_mcp/core/identity.py
zulipchat_mcp/core/security.py
zulipchat_mcp/core/service_manager.py
zulipchat_mcp/core/commands/__init__.py
zulipchat_mcp/core/commands/engine.py
zulipchat_mcp/core/commands/workflows.py
zulipchat_mcp/core/validation/__init__.py
zulipchat_mcp/core/validation/narrow.py
zulipchat_mcp/core/validation/schemas.py
zulipchat_mcp/core/validation/simple_validators.py
zulipchat_mcp/core/validation/types.py
zulipchat_mcp/core/validation/validators.py
zulipchat_mcp/services/__init__.py
zulipchat_mcp/services/agent_registry.py
zulipchat_mcp/services/message_listener.py
zulipchat_mcp/services/scheduler.py
zulipchat_mcp/tools/__init__.py
zulipchat_mcp/tools/agents.py
zulipchat_mcp/tools/ai_analytics.py
zulipchat_mcp/tools/commands.py
zulipchat_mcp/tools/emoji_messaging.py
zulipchat_mcp/tools/event_management.py
zulipchat_mcp/tools/events.py
zulipchat_mcp/tools/files.py
zulipchat_mcp/tools/mark_messaging.py
zulipchat_mcp/tools/messaging.py
zulipchat_mcp/tools/schedule_messaging.py
zulipchat_mcp/tools/search.py
zulipchat_mcp/tools/stream_management.py
zulipchat_mcp/tools/system.py
zulipchat_mcp/tools/topic_management.py
zulipchat_mcp/tools/users.py
zulipchat_mcp/utils/__init__.py
zulipchat_mcp/utils/database.py
zulipchat_mcp/utils/database_manager.py
zulipchat_mcp/utils/health.py
zulipchat_mcp/utils/logging.py
zulipchat_mcp/utils/metrics.py
zulipchat_mcp/utils/narrow_helpers.py
zulipchat_mcp/utils/topics.py
zulipchat_mcp-0.5.0.dist-info/METADATA
zulipchat_mcp-0.5.0.dist-info/WHEEL
zulipchat_mcp-0.5.0.dist-info/entry_points.txt
zulipchat_mcp-0.5.0.dist-info/licenses/LICENSE
zulipchat_mcp-0.5.0.dist-info/RECORD
