Metadata-Version: 2.4
Name: zulipchat-mcp
Version: 0.5.0
Summary: MCP server for Zulip Chat integration with comprehensive tool support
Project-URL: Homepage, https://github.com/akougkas/zulipchat-mcp
Project-URL: Documentation, https://github.com/akougkas/zulipchat-mcp#readme
Project-URL: Repository, https://github.com/akougkas/zulipchat-mcp.git
Project-URL: Issues, https://github.com/akougkas/zulipchat-mcp/issues
Project-URL: Changelog, https://github.com/akougkas/zulipchat-mcp/releases
Author-email: Anthony Kougkas <a.kougkas@gmail.com>
License: MIT
License-File: LICENSE
Keywords: ai,assistant,chat,mcp,zulip
Classifier: Development Status :: 4 - Beta
Classifier: Intended Audience :: Developers
Classifier: Operating System :: OS Independent
Classifier: Programming Language :: Python :: 3
Classifier: Programming Language :: Python :: 3.10
Classifier: Programming Language :: Python :: 3.11
Classifier: Programming Language :: Python :: 3.12
Classifier: Topic :: Communications :: Chat
Classifier: Topic :: Communications :: Conferencing
Classifier: Topic :: Software Development :: Libraries :: Python Modules
Classifier: Topic :: System :: Monitoring
Requires-Python: >=3.10
Requires-Dist: duckdb>=1.3.0
Requires-Dist: fastmcp[anthropic]>=2.14.0
Requires-Dist: httpx>=0.28.0
Requires-Dist: prometheus-client>=0.22.0
Requires-Dist: pydantic>=2.11.0
Requires-Dist: python-dotenv>=1.1.0
Requires-Dist: requests>=2.32.0
Requires-Dist: structlog>=25.4.0
Requires-Dist: zulip>=0.9.0
